main.py
bili_dl2-1.0.1.dist-info/licenses/LICENSE
commands/__init__.py
commands/download_command.py
commands/login_command.py
commands/status_command.py
config/config.json.template
config/config_manager.py
modules/ffmpeg_integration.py
modules/login_manager.py
modules/stream_downloader.py
modules/video_info.py
utils/common_utils.py
bili_dl2-1.0.1.dist-info/METADATA
bili_dl2-1.0.1.dist-info/WHEEL
bili_dl2-1.0.1.dist-info/entry_points.txt
bili_dl2-1.0.1.dist-info/top_level.txt
bili_dl2-1.0.1.dist-info/RECORD
