Metadata-Version: 2.4
Name: bili-dl2
Version: 1.0.1
Summary: 一个功能强大的B站视频下载工具，支持最高清晰度下载和自动合并
Home-page: https://github.com/WavesMan/bili-dl2load
Author: B站视频下载器
Author-email: 
License: MIT License
Project-URL: Homepage, https://github.com/WavesMan/bili-dl2loader
Project-URL: BugTracker, https://github.com/WavesMan/bili-dl2loader/issues
Project-URL: Source, https://github.com/WavesMan/bili-dl2loader
Keywords: bilibili,video,download,b站,视频下载
Classifier: Development Status :: 4 - Beta
Classifier: Intended Audience :: End Users/Desktop
Classifier: License :: OSI Approved :: MIT License
Classifier: Programming Language :: Python :: 3
Classifier: Programming Language :: Python :: 3.7
Classifier: Programming Language :: Python :: 3.8
Classifier: Programming Language :: Python :: 3.9
Classifier: Programming Language :: Python :: 3.10
Classifier: Operating System :: OS Independent
Requires-Python: >=3.8
License-File: LICENSE
Requires-Dist: requests>=2.28.0
Requires-Dist: qrcode>=7.3.1
Requires-Dist: Pillow>=9.3.0
Provides-Extra: dev
Requires-Dist: black>=22.10.0; extra == "dev"
Requires-Dist: flake8>=5.0.0; extra == "dev"
Requires-Dist: mypy>=0.991; extra == "dev"
Requires-Dist: pytest>=7.2.0; extra == "dev"
Dynamic: home-page
Dynamic: license-file
Dynamic: requires-python
